{
  "id": "2xfw8x",
  "nome": "Elisa Moraes",
  "arquetipo": "Adulto Nordeste Ansioso",
  "descricao": "Mulher de 30 anos, faxineiro, mora em João Pessoa, PB. Possui traços marcantes de Extroversao, Amabilidade. ",
  "link_photo": "https://ui-avatars.com/api/?name=Elisa+Moraes&size=256&background=random",
  "created_at": "2025-12-15T00:08:49.048150+00:00",
  "version": "1.0.0",
  "demografia": {
    "idade": 30,
    "genero_biologico": "feminino",
    "identidade_genero": "mulher cis",
    "raca_etnia": "branco",
    "localizacao": {
      "pais": "Brasil",
      "regiao": "Nordeste",
      "estado": "PB",
      "cidade": "João Pessoa"
    },
    "escolaridade": "Fundamental incompleto",
    "renda_mensal": 4113.05,
    "ocupacao": "Faxineiro",
    "estado_civil": "solteiro",
    "composicao_familiar": {
      "tipo": "monoparental",
      "numero_pessoas": 3
    }
  },
  "psicografia": {
    "personalidade_big_five": {
      "abertura": 43,
      "conscienciosidade": 52,
      "extroversao": 63,
      "amabilidade": 62,
      "neuroticismo": 67
    },
    "valores": [
      "liberdade",
      "harmonia",
      "cultura"
    ],
    "interesses": [
      "economia",
      "poesia",
      "ciências",
      "finanças pessoais",
      "escalada"
    ],
    "hobbies": [
      "blogging",
      "trabalho social",
      "bordado"
    ],
    "estilo_vida": "Equilibrado e moderado",
    "inclinacao_politica": -58,
    "inclinacao_religiosa": "católico"
  },
  "comportamento": {
    "habitos_consumo": {
      "frequencia_compras": "esporádica",
      "preferencia_canal": "híbrido",
      "categorias_preferidas": [
        "vestuário e acessórios",
        "ferramentas"
      ]
    },
    "uso_tecnologia": {
      "smartphone": true,
      "computador": true,
      "tablet": false,
      "smartwatch": false
    },
    "padroes_midia": {
      "tv_aberta": 5,
      "streaming": 39,
      "redes_sociais": 38
    },
    "fonte_noticias": [
      "jornais online",
      "newsletters"
    ],
    "comportamento_compra": {
      "impulsivo": 36,
      "pesquisa_antes_comprar": 63
    },
    "lealdade_marca": 63,
    "engajamento_redes_sociais": {
      "plataformas": [
        "Threads",
        "Twitter/X",
        "WhatsApp",
        "TikTok",
        "YouTube"
      ],
      "frequencia_posts": "frequente"
    }
  },
  "deficiencias": {
    "visual": {
      "tipo": "nenhuma"
    },
    "auditiva": {
      "tipo": "nenhuma"
    },
    "motora": {
      "tipo": "nenhuma",
      "usa_cadeira_rodas": false
    },
    "cognitiva": {
      "tipo": "nenhuma"
    }
  },
  "capacidades_tecnologicas": {
    "alfabetizacao_digital": 70,
    "dispositivos": {
      "principal": "computador",
      "qualidade": "novo"
    },
    "preferencias_acessibilidade": {
      "zoom_fonte": 100,
      "alto_contraste": false
    },
    "velocidade_digitacao": 55,
    "frequencia_internet": "semanal",
    "familiaridade_plataformas": {
      "e_commerce": 46,
      "banco_digital": 64,
      "redes_sociais": 41
    }
  },
  "vieses": {
    "aversao_perda": 40,
    "desconto_hiperbolico": 70,
    "suscetibilidade_chamariz": 68,
    "ancoragem": 61,
    "vies_confirmacao": 35,
    "vies_status_quo": 41,
    "sobrecarga_informacao": 47
  }
}