{
  "id": "qk8xcs",
  "nome": "Camila Sampaio",
  "arquetipo": "Meia-Idade Sudeste Ansioso",
  "link_photo": "https://ui-avatars.com/api/?name=Camila+Sampaio&size=256&background=random",
  "created_at": "2025-12-15T04:44:32.064323+00:00",
  "version": "1.0.0",
  "demografia": {
    "idade": 50,
    "genero_biologico": "feminino",
    "identidade_genero": "mulher cis",
    "raca_etnia": "branco",
    "localizacao": {
      "pais": "Brasil",
      "regiao": "Sudeste",
      "estado": "RJ",
      "cidade": "Niterói"
    },
    "escolaridade": "Superior completo",
    "renda_mensal": 35391.77,
    "ocupacao": "Gerente administrativo",
    "estado_civil": "solteiro",
    "composicao_familiar": {
      "tipo": "monoparental",
      "numero_pessoas": 2
    }
  },
  "psicografia": {
    "personalidade_big_five": {
      "abertura": 31,
      "conscienciosidade": 51,
      "extroversao": 34,
      "amabilidade": 54,
      "neuroticismo": 74
    },
    "valores": [
      "educação",
      "saúde",
      "segurança"
    ],
    "interesses": [
      "poesia",
      "culinária",
      "meditação",
      "viagens"
    ],
    "hobbies": [
      "aeromodelismo",
      "meditação",
      "decoração",
      "investimentos",
      "trading"
    ],
    "estilo_vida": "Reservado e cauteloso",
    "inclinacao_politica": -26,
    "inclinacao_religiosa": "católico"
  },
  "comportamento": {
    "habitos_consumo": {
      "frequencia_compras": "diária",
      "preferencia_canal": "híbrido",
      "categorias_preferidas": [
        "ferramentas",
        "vestuário e acessórios"
      ]
    },
    "uso_tecnologia": {
      "smartphone": true,
      "computador": true,
      "tablet": false,
      "smartwatch": false
    },
    "padroes_midia": {
      "tv_aberta": 1,
      "streaming": 46,
      "redes_sociais": 21
    },
    "fonte_noticias": [
      "TV por assinatura",
      "podcasts"
    ],
    "comportamento_compra": {
      "impulsivo": 63,
      "pesquisa_antes_comprar": 42
    },
    "lealdade_marca": 46,
    "engajamento_redes_sociais": {
      "plataformas": [
        "LinkedIn",
        "Instagram",
        "WhatsApp"
      ],
      "frequencia_posts": "raro"
    }
  },
  "deficiencias": {
    "visual": {
      "tipo": "nenhuma"
    },
    "auditiva": {
      "tipo": "nenhuma"
    },
    "motora": {
      "tipo": "nenhuma",
      "usa_cadeira_rodas": false
    },
    "cognitiva": {
      "tipo": "nenhuma"
    }
  },
  "capacidades_tecnologicas": {
    "alfabetizacao_digital": 85,
    "dispositivos": {
      "principal": "computador",
      "qualidade": "novo"
    },
    "preferencias_acessibilidade": {
      "zoom_fonte": 100,
      "alto_contraste": false
    },
    "velocidade_digitacao": 45,
    "frequencia_internet": "mensal",
    "familiaridade_plataformas": {
      "e_commerce": 66,
      "banco_digital": 77,
      "redes_sociais": 40
    }
  },
  "vieses": {
    "aversao_perda": 60,
    "desconto_hiperbolico": 55,
    "suscetibilidade_chamariz": 37,
    "ancoragem": 66,
    "vies_confirmacao": 51,
    "vies_status_quo": 35,
    "sobrecarga_informacao": 29
  },
  "descricao": "Mulher de 50 anos, gerente administrativo, mora em Niterói, RJ. Possui traços marcantes de Neuroticismo. "
}